{
  "$schema": "https://dev.office.com/json-schemas/spfx/client-side-web-part-manifest.schema.json",
  "id": "39b80ba4-8d62-43f3-8b17-673fecefe627",
  "alias": "FactoryMethodWebPart",
  "componentType": "WebPart",

  // The "*" signifies that the version should be taken from the package.json
  "version": "*",
  "manifestVersion": 2,

  // If true, the component can only be installed on sites where Custom Script is allowed.
  // Components that allow authors to embed arbitrary script code should set this to true.
  // https://support.office.com/en-us/article/Turn-scripting-capabilities-on-or-off-1f2c515f-5d7e-448a-9fd7-835da935584f
  "requiresCustomScript": false,

  "preconfiguredEntries": [{
    "groupId": "39b80ba4-8d62-43f3-8b17-673fecefe627",
    "group": { "default": "Design Patterns Webparts" },
    "title": { "default": "FactoryMethod" },
    "description": { "default": "Factory Method design pattern web part" },
    "officeFabricIconFontName": "Page",
    "properties": {
      "description": "FactoryMethod"
    }
  }]
}
